LICENSE
ios_shell/__init__.py
ios_shell/keys.py
ios_shell/parsing.py
ios_shell/regex.py
ios_shell/sections.py
ios_shell/shell.py
ios_shell/utils.py
ios_shell-1.2.2.dist-info/LICENSE
ios_shell-1.2.2.dist-info/WHEEL
ios_shell-1.2.2.dist-info/METADATA
ios_shell-1.2.2.dist-info/RECORD
