Metadata-Version: 2.1
Name: ios-shell
Version: 1.2.2
Summary: Parses files formatted by the Institute of Ocean Sciences' IOSShell tool
Home-page: https://github.com/cyborgsphinx/ios-shell
License: MIT
Keywords: ocean,science,parse
Author: James Hannah
Author-email: jhannah@protonmail.com
Requires-Python: >=3.8,<3.11
Classifier: License :: OSI Approved :: MIT License
Classifier: Operating System :: OS Independent
Classifier: Programming Language :: Python :: 3
Classifier: Programming Language :: Python :: 3.10
Classifier: Programming Language :: Python :: 3.8
Classifier: Programming Language :: Python :: 3.9
Classifier: Topic :: Scientific/Engineering :: Information Analysis
Classifier: Topic :: Text Processing :: General
Provides-Extra: pandas
Requires-Dist: fortranformat (>=1.0.1,<2.0.0)
Requires-Dist: pandas (>=1.4.2,<2.0.0); extra == "pandas"
Project-URL: Documentation, https://ios-shell.readthedocs.io
Project-URL: Repository, https://github.com/cyborgsphinx/ios-shell
